ControlUnit/OutputLogic.v
module OutputLogic(
  state,  //current state
  status, //signals from processor status register
  ir, //the value of the instruction register
  ctrlword,  //a 18-bit control word to manage the datapath
  rw_mem //signal asserted when the main memory is asserted
);

  input  wire[12:0] state;
  input  wire[4:0]  status;
  input  wire[15:0] ir; //instruction
  output wire[19:0] ctrlword;
  output wire       rw_mem;

  //Address A[3]
  assign ctrlword[19] = state[0]  | 
                        state[2]  & ir[4] |
                        state[5]  |
                        state[6]  & (ir[10] | ir[9] |ir[8]) |
                        state[7]  |
                        state[8]  |
                        state[9]  |
                        state[10] |
                        state[11] |
                        state[12] & (~status[4] | status[4] & (ir[10] | ir[9] | ir[8]));
  //Address A[2]
  assign ctrlword[18] = state[0]  |
                        state[2]  & (~ir[4] & ir[2] | ir[4])|
                        state[3]  & ir[7] |
                        state[4]  & ir[7] |
                        state[5]  |
                        state[6]  |
                        state[7]  |
                        state[8] & ~ir[11] |
                        state[9]  |
                        state[10] |
                        state[11] |
                        state[12] & (~status[4] | status[4] & (ir[10] | ir[9] | ir[8]));

  //Address A[1]
  assign ctrlword[17] = state[0] |
                        state[2] & (~ir[4] & ir[1] | ir[4]) |
                        state[3] & ir[6] |
                        state[4] & ir[6] |
                        state[6] |
                        state[8] |
                        state[9] & ir[11] |
                        state[10] |
                        state[11] |
                        state[12] & (~status[4] | status[4] & (ir[10] | ir[9] | ir[8]));
  
  //Address A[0]
  assign ctrlword[16] = state[2] & (~ir[4] & ir[0] | ir[4]) |
                        state[3] & ir[5] |
                        state[4] & ir[5] |
                        state[5] |
                        state[6] |
                        state[7] |
                        state[8] & ~ir[11]|
                        state[9] |
                        state[11];
 
  //Address B[3]
  assign ctrlword[15] = state[2] & ir[4] |
                        state[3] |
                        state[6] & ~(ir[10] | ir[9] |ir[8])|
                        state[7] |
                        state[8] |
                        state[9] |
                        state[10] |
                        state[11] |
                        state[12];
  //Address B[2]
  assign ctrlword[14] = state[2] & ir[2] |
                        state[3] |
                        state[4] & ir[2] |
                        state[5] & ir[10] |
                        state[6] & ~(ir[10 | ir[9] | ir[8]]) |
                        state[7] |
                        state[9] |
                        state[10] |
                        state[11] |
                        state[12] & ~status[4];
  //Address B[1]
  assign ctrlword[13] = state[2] & (~ir[4] & ir[1] | ir[4]) |
                        state[4] & ir[1] |
                        state[5] & ir[9] |
                        state[8] & ir[11] |
                        state[10] |
                        state[11];
  //Address B[0]
  assign ctrlword[12] = state[2] & (~ir[4] & ir[0] | ir[4] & ir[3]) |
                        state[3] |
                        state[4] & ir[0] |
                        state[5] & ir[8] |
                        state[7] |
                        state[8] |
                        state[9] |
                        state[11];
  //Address D[3]
  assign ctrlword[11]  = ~(state[1] |
                          state[3] | 
                          state[5] |
                          state[9] |
                          state[10]);

  //Address D[2]
  assign ctrlword[10]  = state[0] |
                        state[2] |
                        state[3] & ir[10] |
                        state[4] |
                        state[5] & ir[10] |
                        state[6] |
                        state[8] |
                        state[9] & ir[10] |
                        state[10] |
                        state[12];
  
  //Address D[1]
  assign ctrlword[9]  = state[0] |
                        state[3] & ir[9] |
                        state[5] & ir[9] |
                        state[9] & ir[9] |
                        state[10] |
                        state[12];
  
  //Address D[0]
  assign ctrlword[8]  = state[0] |
                        state[2] |
                        state[3] & ir[8] |
                        state[4] |
                        state[5] & ir[8] |
                        state[6] |
                        state[8] |
                        state[9] & ir[8] |
                        state[10];
  //rw file register
  assign ctrlword[7]  = ~(state[1] | 
                          state[5] & ir[11]);
  //Data selection
  assign ctrlword[6]  = state[0] |
                        state[5] & ~ir[11];

  //Write PSR
  //TODO Revisar la ecuación
  assign ctrlword[5]  =     (state[3] & ~ir[4]  &  ir[3]) |
                             state[7] & ((~ir[10] & ~ir[9] & ~ir[8]) | //jump
                                         (~ir[10] & ~ir[9] &  ir[8]) | //ba
                            (~status[0] & ~ir[10] &  ir[9] & ~ir[8]) | //bne
                             (status[0] & ~ir[10] &  ir[9] &  ir[8]) | //be
 (~status[0] & ~(status[1] ^ status[2]) &  ir[10] & ~ir[9] & ~ir[8] )| //bg
((status[0] |  (status[1] ^ status[2])) &  ir[10] & ~ir[9] &  ir[8]) | //ble
              (~(status[1] ^ status[2]) &  ir[10] &  ir[9] & ~ir[8]) | //bge
               ((status[1] ^ status[2]) &  ir[10] &  ir[9] &  ir[8]) ) |//bl
                             state[11] |
                             state[12] & status[4];
  //set displacement             
  assign ctrlword[4] = state[7] | state[11];

  
  //operational code[3]
  assign ctrlword[3]  = state[3] & ir[14] |
                        state[6] & (ir[10] | ir[9] |ir[8]) |
                        state[9] & ir[11];
  
  //operational code[2]
  assign ctrlword[2]  = state[3] & ir[13] |
                        state[4] |
                        state[6] & (ir[10] | ir[9] | ir[8]) |
                        state[9] & ir[11] |
                        state[11] |
                        state[12];

  //operational code[1]
  assign ctrlword[1]  = state[3] & ir[12] |
                        state[6] & (ir[10] | ir[9] | ir[8]);

  //operational code[0]
  assign ctrlword[0]  = state[2] & ir[4] & ir[3] |
                        state[3] & ir[11] |
                        state[4] & ir[4];

  assign rw_mem = state[5] & ir[11];

endmodule // OutputLogic

ControlUnit/State.v
module State(
  d, //each of the inputs of the FFD integrating the memory of the M machine
  q, //each of the outputs of the FFD
  clk, //clock signal
  preset //Signal that reset the control unit to the IF state
);

  input  wire[12:0] d; //next state logic
  input  wire       clk, preset; //Obvious, isn't it?
  output reg[12:0]  q; //current state

  always @(posedge clk) begin
    if (preset) 
      q <= 13'b0000000000001;
    else
      q <= d;
  end

endmodule // State

ControlUnit/NextStateLogic.v
module NextStateLogic(
  opc1,     //operational code indicating the instruction format
  opc2,     //operational code indicating the functional operation 
  state,    //Memory of the Mealey machine
  nextstate //Output of the next-state-logic module
);

  input  wire[12:0] state;
  input  wire       opc1;
  input  wire[3:0]  opc2;
  output wire[12:0] nextstate;

  //Instruction fetch
  assign nextstate[0] = state[12];

  //Instruction decode
  assign nextstate[1] = state[0];

  //Operand fetch in microop
  assign nextstate[2] = state[1] & ~opc1 & (~(opc2[3] ^ opc2[2]) | //Logic and shift
                                   ~opc2[3] & opc2[2] & ~opc2[1] | //add
                                   ~opc2[1] & ~opc2[0] ); //mult
  //Instruction execution in microop
  assign nextstate[3] = state[2];

  //Operand fetch in memory instructions
  assign nextstate[4] = state[1] & ~opc2[3] & opc2[2] & opc2[1];
  
  //Instruction execution in memory instructions
  assign nextstate[5] = state[4];

  //Operand fetch in jump instructions
  assign nextstate[6] = state[1] & opc2[3] & ~opc2[2] & ~opc2[1] & opc2[0];

  //Instruction execution in jump instructions
  assign nextstate[7] = state[6];

  //Operand fetch in set-constant instructions
  assign nextstate[8] = state[1] & opc2[3] & ~opc2[2] & opc2[1];

  //Instruction execution in set-constant instructions
  assign nextstate[9] = state[8];

  //Link program counter
  assign nextstate[10] = state[1] & opc1;

  //Link PC in call instruction
  assign nextstate[11] = state[10];

  //Update program counter
  assign nextstate[12] = state[3] | state[5] | state[7] | state[9] | state[11];
  
endmodule // NextStateLogic

ControlUnit/ControlUnit.v
//`include "NextStateLogic.v"
//`include "State.v"
//`include "OutputLogic.v"
`include "ControlUnit/NextStateLogic.v"
`include "ControlUnit/State.v"
`include "ControlUnit/OutputLogic.v"

module ControlUnit(
  clk,         //clock signal
  reset,       //signal resetting the control unit to the IF state
  instruction, //an instruction from the IR register
  status,      //processor status
  ctrlword,    //control word to manage the datapath
  rw_mem       //signal that indicates the operation mode of the main memory
);

  //Port definition
  input  wire       clk, reset;
  input  wire[4:0]  status; //d, v, c, z, n
  input  wire[15:0] instruction;
  output wire[19:0] ctrlword;
  output wire       rw_mem;

  //Internal signals
  wire[12:0] state, nextstate;

  NextStateLogic nsl_unit(
    instruction[15],    //instruction format
    instruction[14:11], //functional operation
    state,              //memory
    nextstate           //output of the nsl module
  );

  State state_unit(
    nextstate, //the input of the memory
    state,     //the output of the memory
    clk,       //the clock signal
    reset      //the reset signal
  );

  OutputLogic ol_unit(
    state,       //output memory
    status,      //output from the PSR register
    instruction, //an instruction from the IR register
    ctrlword,    //the control word generated by the control unit
    rw_mem
  );

endmodule // ControUnit

Datapath/Basic/Mux2x1p.v
`ifndef MUX2X1_V
`define	MUX2X1_V

module Mux2x1(a, b, sel, y);
	
  parameter width = 1;
  input wire[width-1:0] a, b;
  input wire sel;
	output reg[width-1:0] y;
	
	always @(*)
	begin
		if (sel == 1'b0)
			y = a;
		else 
			y = b;
	end

endmodule

`endif

Datapath/PSR/ProcessorStatusRegister.v
//Author: Adán G. Medrano-Chávez
`ifndef PSR_V
`define PSR_V

module ProcessorStatusRegister(
    clk,          //clk signal
    reset,        //reset signal
    rw,           //PSR_rw signal
    displacement, //the set-displacement signal
    flags,        //status of an operation (V, C, Z, N)
    status        //the content of the PSR register
);


    input wire clk, reset, rw, displacement;
    input wire[3:0] flags;
    output reg[4:0] status;
    
    always @ (negedge clk or reset) begin
        if  (rw && displacement) status[4] <= displacement;
        else if (rw) status <= {displacement, flags};
        if (reset) begin
            status <= 5'b00000;
        end
    end

endmodule

`endif

Datapath/SimpleFunctionalUnit/FunctionalUnit.v
`ifndef SIMPLE_FU_V
`define SIMPLE_FU_V

module FunctionalUnit(
  a, //main operand to perform microoperations
  b, //supporting operand
  opcode, //operational code for microoperations
  result, //a result
  status //flags CVZN
);

  input wire[15:0] a, b;
  input wire[3:0] opcode;
  output reg[15:0] result;
  output reg[3:0] status;

  reg[16:0] carry; //Internal reg keeping all generated carries
  integer i;

  //Computes result
  always @(*) begin
    casex (opcode)
      4'b0000: result = a & b;
      4'b0001: result = a | b;
      4'b0010: result = ~a;
      4'b0011: result = a ^ b;
      4'b01x0: result = a + b + opcode[0];
      4'b01x1: result = a + ~b + opcode[0];
      4'b10xx: result = a[7:0] * b[7:0];
      4'b1100: result = a << b[3:0];
      4'b1101: result = a >> b[3:0];
      4'b1110: result = {{8{a[7]}},a[7:0]};//sign extension
      default: result = a + 2;//incpc  
    endcase
  end

  //Computes flags
  //Note that this code is not sinthetizable
  //TODO: Compute carries hierarchically 
  always @(*) begin
    carry[0]  = opcode[0];
    status[0] = ~|result;//Z
    status[1] = result[15];//N
    for (i = 0; i < 16 ; i = i + 1) begin
      carry[i+1] = a[i]&b[i] | (a[i]^b[i]) & carry[i];
    end
    status[3] = carry[16];//C
    status[2] = carry[16] ^ carry[15];//V
  end

endmodule // FunctionalUnit

`endif

Datapath/FileRegister.old/FileRegister.v
`ifndef FILE_REGISTER_V
`define FILE_REGISTER_V

module FileRegister(
    clk,
    reset,
    addrA,
    addrB,
    addrD,
    rw,
    data,
    busA,
    busB,
    ir
);

    localparam width = 16;
    input wire clk, reset, rw; //Clock signal and read/write signal
    input wire[3:0] addrA, addrB, addrD; //Address of buses A, B, and D
    input wire[width-1:0] data;
    output reg[width-1:0] busA, busB;
    reg[15:0] r0;
    reg[15:0] r1;
    reg[15:0] r2;
    reg[15:0] r3;
    reg[15:0] r4;
    reg[15:0] r5;
    reg[15:0] r6;
    reg[15:0] r7;
    reg[width-1:0] displacement;
    reg[width-1:0] maskl;
    reg[width-1:0] pimm4;
    reg[width-1:0] nimm4;
    reg[width-1:0] const2;
    reg[width-1:0] temp0;
    reg[width-1:0] pc;
    output reg[width-1:0] ir;
        
    
    always @ (reset) begin
        if (reset) begin
            r0  <= 16'h0000;
            r1  <= 16'h0000;
            r2  <= 16'h0000;
            r3  <= 16'h0000;
            r4  <= 16'h0000;
            r5  <= 16'h0000;
            r6  <= 16'h0000;
            r7  <= 16'h0000;
            displacement <= 16'h0000;
            maskl        <= 16'h00FF;
            pimm4        <= 16'h000F;
            nimm4        <= 16'hFFF8;
            const2       <= 16'h0002;
            temp0        <= 16'h0000;
            pc           <= 16'h0000;
            ir           <= 16'h0000;
        end
    end
    
    always @ (negedge clk) begin
        case (addrD)
            1:  if(rw) r1 <= data;
            2:  if(rw) r2 <= data; 
            3:  if(rw) r3 <= data;
            4:  if(rw) r4 <= data;
            5:  if(rw) r5 <= data;
            6:  if(rw) r6 <= data;
            7:  if(rw) r7 <= data;
            8:  if(rw) displacement <= data;
            13: if(rw) temp0 <= data;
            14: if(rw) pc <= data;
            15: if(rw) ir <= data;
            default: begin
                r0 <= 16'h0000;
                maskl <= 16'h00FF; //maskl
                pimm4 <= 16'h000F; //pimm4
                nimm4 <= 16'hFFF8; //nimm4
                const2 <= 16'h0002;//const2
            end
        endcase
    end

    always @ (*) begin
        //Bus A
        case (addrA)
          0:  busA <= r0;
          1:  busA <= r1;
          2:  busA <= r2;
          3:  busA <= r3;
          4:  busA <= r4;
          5:  busA <= r5;
          6:  busA <= r6;
          7:  busA <= r7;
          8:  busA <= displacement;
          9:  busA <= maskl;
          10: busA <= pimm4;
          11: busA <= nimm4;
          12: busA <= const2;
          13: busA <= temp0;
          14: busA <= pc;
          default: busA <= ir;
        endcase

        //Bus B
        if (addrB == 4'h0) busB = r0;
        else if (addrB == 4'h1) busB = r1;
        else if (addrB == 4'h2) busB = r2;
        else if (addrB == 4'h3) busB = r3;
        else if (addrB == 4'h4) busB = r4;
        else if (addrB == 4'h5) busB = r5;
        else if (addrB == 4'h6) busB = r6;
        else if (addrB == 4'h7) busB = r7;
        else if (addrB == 4'h8) busB = displacement;
        else if (addrB == 4'h9) busB = maskl;
        else if (addrB == 4'hA) busB = pimm4;
        else if (addrB == 4'hB) busB = nimm4;
        else if (addrB == 4'hC) busB = const2;
        else if (addrB == 4'hD) busB = temp0;
        else if (addrB == 4'hE) busB = pc;
        else busB = ir;
    end

endmodule //Fileregister

`endif

Datapath/Datapath.v
`ifndef DATAPATH_V
`define DATAPATH_V

`ifdef PROCESSOR_V
  `include "Datapath/SimpleFunctionalUnit/FunctionalUnit.v"
  `include "Datapath/FileRegister/FileRegister.v"
  `include "Datapath/Basic/Mux2x1p.v"
  `include "Datapath/PSR/ProcessorStatusRegister.v"
`else
  `include "SimpleFunctionalUnit/FunctionalUnit.v"
  `include "FileRegister/FileRegister.v"
  `include "Basic/Mux2x1p.v"
  `include "PSR/ProcessorStatusRegister.v"
`endif

//The first line in the port module is the control word determining
//the datapath behavior
//The second line is the clock signal
//The last line is the output of the datapath, status contains the
//the flags VCNZ, the bus A conveys the data address to the 
//main memory and busB contains the data to be stored

module Datapath(
  clk,
  reset,
  ctrlword,
  instruction,
  status,
  dataIn,
  busA,
  busB
);

    input wire clk, reset;
    //{addrA}{addrb}{addrD}{FRrw}{seld}{PSRrw}{d}{opcode}
    input wire[19:0] ctrlword;
    input wire[15:0] dataIn;
    
    output wire[15:0] instruction, busA, busB;
    output wire[4:0] status;//D V C N Z flags
    
    /*Internal signals*/
    wire[15:0] result; //Result of the Functional Unit
    wire[15:0] dataBus; //Output of the MUX D
    wire[3:0] flags; //The status of an operation (V C N Z)

    FileRegister file_register_u(
        dataBus,          //data bus
        busA,             //address bus
        busB,             //data output bus
        instruction,      //the content of the IR register
        ctrlword[19:16],  //addrA
        ctrlword[15:12],  //addrB
        ctrlword[11:8],   //addrD
        reset,            //reset signal
        ctrlword[7],      //~read signal
        clk               //clock signal
    );

    //FunctionalUnit(a, b, opcode, y, status)
    FunctionalUnit functional_u(
        busA,          //Operand A from file register
        busB,          //output data bus
        ctrlword[3:0], //opcode
        result,        //Result from the funtional unit
        flags          //The status of an operation
    );
    
    //ProcessorStatusRegister(clk, reset, rw, displacement, flags, status)
    ProcessorStatusRegister psr_u(
        clk,         //clk signal
        reset,       //reset signal
        ctrlword[5], //PSR_rw signal
        ctrlword[4], //the set-displacement signal
        flags,       //status of an operation
        status       //the content of the PSR register
    );

    //module Mux2x1(a, b, sel, y);
    defparam muxd.width = 16;
    Mux2x1 muxd(
        result,      //Result from the functional unit
        dataIn,      //Data from the main memory
        ctrlword[6], //Data selection signal
        dataBus      //Input of the file register
    );

endmodule //module Datapath

`endif

Processor.v
`include "Datapath/Datapath.v"
`include "ControlUnit/ControlUnit.v"

module Processor(
  dataIn, //data or instructions comming from the main memory
  busA,   //Data comming from the bus A of the datapath
  busB,   //Data comming from the bus B of the datapath
  rw,     //signal indicating whether the main memory is to be written or not
  reset,  //signal reseting the processor
  clk     //clock signal
);

  input wire[15:0] dataIn;
  input wire clk, reset;
  output wire[15:0] busA, busB;
  output wire rw;
  
  //Internal signals
  wire[19:0] ctrlword;
  wire[15:0] instruction;
  wire[4:0] status; //d v c n z
  
  Datapath datapath_unit(
    clk,
    reset,
    ctrlword,
    instruction,
    status,
    dataIn,
    busA,
    busB
  );

  ControlUnit control_unit(
    clk,
    reset,
    instruction,
    status,
    ctrlword,
    rw
  );

endmodule //Processor

mult.v
`include "Processor.v"
`timescale 1ns/100ps

module testbench;

  //outputs
  wire[15:0] busA, busB;
  wire rw;
  //inputs
  reg[15:0] dataIn;
  reg reset, clk;
  integer pc;
  
  Processor mARC(//marcee
    dataIn, //data or instructions comming from the main memory
    busA,   //Data comming from the bus A of the datapath
    busB,   //Data comming from the bus B of the datapath
    rw,     //signal indicating whether the main memory is to be written or not
    reset,  //signal reseting the processor
    clk    //clock signal
  );
  
  always #1 clk = ~clk;
  
  initial begin
    $dumpfile("marcee.vcd");
    $dumpvars(0, testbench);
    pc = 0;
    clk = 1;
    reset = 1;
    dataIn = 16'b0_1010_001_00001111; //setlow 15, %r1
    #10;
    reset = 0;
    dataIn = 16'b0_1010_010_00000011; //setlow 3, %r2
    #10;
    dataIn = 16'b0_1001_001_00000110; //ba 6 !%pc <-- %pc + 6
    #10;
    pc = busA;
    while(pc != 14) begin
      if (pc == 6) begin
        dataIn = 16'b0_0100_100_001_0_0_100; //add %r1, %r4, %r4 !acc <-- acc + r1
        #10;
        dataIn = 16'b0_0100_011_011_1_0001; //add %r3, 1, %r3
        #10;
      end
      dataIn = 16'b0_0101_000_011_0_1_010; //subcc %r3, %r2, %r0
      #10;
      dataIn = 16'b0_1001_111_11111010; //bl -6
      #10;
      pc = busA;
    end
    dataIn = 16'b0_1011_110_00001000; //sethi 8, %r6 !%r6 <-- 2048
    #10;
    dataIn = 16'b0_0111_100_110_0_0000; //st %r4, %r6
    #10 $finish;
  end
endmodule //testbench

marcee.vcd
$date
	Fri Dec  9 12:29:50 2016
$end
$version
	Icarus Verilog
$end
$timescale
	100ps
$end
$scope module testbench $end
$var wire 1 ! rw $end
$var wire 16 " busB [15:0] $end
$var wire 16 # busA [15:0] $end
$var reg 1 $ clk $end
$var reg 16 % dataIn [15:0] $end
$var reg 1 & reset $end
$var integer 32 ' pc [31:0] $end
$scope module mARC $end
$var wire 1 $ clk $end
$var wire 16 ( dataIn [15:0] $end
$var wire 1 & reset $end
$var wire 5 ) status [4:0] $end
$var wire 1 ! rw $end
$var wire 16 * instruction [15:0] $end
$var wire 20 + ctrlword [19:0] $end
$var wire 16 , busB [15:0] $end
$var wire 16 - busA [15:0] $end
$scope module control_unit $end
$var wire 1 $ clk $end
$var wire 1 & reset $end
$var wire 5 . status [4:0] $end
$var wire 13 / state [12:0] $end
$var wire 1 ! rw_mem $end
$var wire 13 0 nextstate [12:0] $end
$var wire 16 1 instruction [15:0] $end
$var wire 20 2 ctrlword [19:0] $end
$scope module nsl_unit $end
$var wire 1 3 opc1 $end
$var wire 4 4 opc2 [3:0] $end
$var wire 13 5 state [12:0] $end
$var wire 13 6 nextstate [12:0] $end
$upscope $end
$scope module ol_unit $end
$var wire 1 ! rw_mem $end
$var wire 5 7 status [4:0] $end
$var wire 13 8 state [12:0] $end
$var wire 16 9 ir [15:0] $end
$var wire 20 : ctrlword [19:0] $end
$upscope $end
$scope module state_unit $end
$var wire 1 $ clk $end
$var wire 13 ; d [12:0] $end
$var wire 1 & preset $end
$var reg 13 < q [12:0] $end
$upscope $end
$upscope $end
$scope module datapath_unit $end
$var wire 1 $ clk $end
$var wire 20 = ctrlword [19:0] $end
$var wire 16 > dataIn [15:0] $end
$var wire 1 & reset $end
$var wire 5 ? status [4:0] $end
$var wire 16 @ result [15:0] $end
$var wire 16 A instruction [15:0] $end
$var wire 4 B flags [3:0] $end
$var wire 16 C dataBus [15:0] $end
$var wire 16 D busB [15:0] $end
$var wire 16 E busA [15:0] $end
$scope module file_register_u $end
$var wire 4 F addrA [3:0] $end
$var wire 4 G addrB [3:0] $end
$var wire 4 H addrD [3:0] $end
$var wire 1 $ clk $end
$var wire 1 & reset $end
$var wire 1 I rw $end
$var wire 16 J data [15:0] $end
$var reg 16 K busA [15:0] $end
$var reg 16 L busB [15:0] $end
$var reg 16 M const2 [15:0] $end
$var reg 16 N displacement [15:0] $end
$var reg 16 O ir [15:0] $end
$var reg 16 P maskl [15:0] $end
$var reg 16 Q nimm4 [15:0] $end
$var reg 16 R pc [15:0] $end
$var reg 16 S pimm4 [15:0] $end
$var reg 16 T r0 [15:0] $end
$var reg 16 U r1 [15:0] $end
$var reg 16 V r2 [15:0] $end
$var reg 16 W r3 [15:0] $end
$var reg 16 X r4 [15:0] $end
$var reg 16 Y r5 [15:0] $end
$var reg 16 Z r6 [15:0] $end
$var reg 16 [ r7 [15:0] $end
$var reg 16 \ temp0 [15:0] $end
$upscope $end
$scope module functional_u $end
$var wire 16 ] a [15:0] $end
$var wire 16 ^ b [15:0] $end
$var wire 4 _ opcode [3:0] $end
$var reg 17 ` carry [16:0] $end
$var reg 16 a result [15:0] $end
$var reg 4 b status [3:0] $end
$var integer 32 c i [31:0] $end
$upscope $end
$scope module muxd $end
$var wire 16 d a [15:0] $end
$var wire 16 e b [15:0] $end
$var wire 1 f sel $end
$var reg 16 g y [15:0] $end
$upscope $end
$scope module psr_u $end
$var wire 1 $ clk $end
$var wire 1 h displacement $end
$var wire 4 i flags [3:0] $end
$var wire 1 & reset $end
$var wire 1 j rw $end
$var reg 5 k status [4:0] $end
$upscope $end
$upscope $end
$upscope $end
$upscope $end
$enddefinitions $end
#0
$dumpvars
b0 k
0j
b1 i
0h
b101000100001111 g
1f
b101000100001111 e
b0 d
b10000 c
b1 b
b0 a
b0 `
b0 _
b0 ^
b0 ]
b0 \
b0 [
b0 Z
b0 Y
b0 X
b0 W
b0 V
b0 U
b0 T
b1111 S
b0 R
b1111111111111000 Q
b11111111 P
b0 O
b0 N
b10 M
b0 L
b0 K
b101000100001111 J
1I
b1111 H
b0 G
b1110 F
b0 E
b0 D
b101000100001111 C
b1 B
b0 A
b0 @
b0 ?
b101000100001111 >
b11100000111111000000 =
b1 <
b10 ;
b11100000111111000000 :
b0 9
b1 8
b0 7
b10 6
b1 5
b0 4
03
b11100000111111000000 2
b0 1
b10 0
b1 /
b0 .
b0 -
b0 ,
b11100000111111000000 +
b0 *
b0 )
b101000100001111 (
b0 '
1&
b101000100001111 %
1$
b0 #
b0 "
0!
$end
#10
b1010 4
b101000100001111 *
b101000100001111 1
b101000100001111 9
b101000100001111 A
b101000100001111 O
0$
#20
b0 F
b0 H
b0 C
b0 J
b0 g
0I
0f
b0 +
b0 2
b0 :
b0 =
b100000000 0
b100000000 6
b100000000 ;
b10 /
b10 5
b10 8
b10 <
1$
#30
0$
#40
b1111 C
b1111 J
b1111 g
b1111111110 `
b0 B
b0 b
b0 i
b1111 @
b1111 a
b1111 d
b101000100001111 #
b101000100001111 -
b101000100001111 E
b101000100001111 K
b101000100001111 ]
b10000 c
b11111111 "
b11111111 ,
b11111111 D
b11111111 L
b11111111 ^
b1111 F
b1101 H
b1001 G
1I
b11111001110110000000 +
b11111001110110000000 2
b11111001110110000000 :
b11111001110110000000 =
b1000000000 0
b1000000000 6
b1000000000 ;
b100000000 /
b100000000 5
b100000000 8
b100000000 <
1$
#50
b1111 \
0$
#60
b1111 #
b1111 -
b1111 E
b1111 K
b1111 ]
b11110 `
b10000 c
b1111 "
b1111 ,
b1111 D
b1111 L
b1111 ^
b1101 F
b1101 G
b1 H
b11011101000110000000 +
b11011101000110000000 2
b11011101000110000000 :
b11011101000110000000 =
b1000000000000 0
b1000000000000 6
b1000000000000 ;
b1000000000 /
b1000000000 5
b1000000000 8
b1000000000 <
1$
#70
b1111 U
0$
#80
b0 #
b0 -
b0 E
b0 K
b0 ]
b0 `
b10 C
b10 J
b10 g
b10 "
b10 ,
b10 D
b10 L
b10 ^
b10000 c
b10 @
b10 a
b10 d
b1100 G
b1110 F
b100 _
b1110 H
b11101100111010000100 +
b11101100111010000100 2
b11101100111010000100 :
b11101100111010000100 =
b1 0
b1 6
b1 ;
b1000000000000 /
b1000000000000 5
b1000000000000 8
b1000000000000 <
1$
#90
b100 C
b100 J
b100 g
b100 `
b10000 c
b100 @
b100 a
b100 d
b10 #
b10 -
b10 E
b10 K
b10 ]
b10 R
0$
#100
b10 #
b10 -
b10 E
b10 K
b10 ]
b0 `
b10000 c
b1 B
b1 b
b1 i
b0 @
b0 a
b0 d
b101001000000011 C
b101001000000011 J
b101001000000011 g
b0 "
b0 ,
b0 D
b0 L
b0 ^
b1110 F
b0 _
1f
b1111 H
b0 G
b11100000111111000000 +
b11100000111111000000 2
b11100000111111000000 :
b11100000111111000000 =
b10 0
b10 6
b10 ;
b1 /
b1 5
b1 8
b1 <
1$
b101001000000011 %
b101001000000011 (
b101001000000011 >
b101001000000011 e
0&
#110
b101001000000011 *
b101001000000011 1
b101001000000011 9
b101001000000011 A
b101001000000011 O
0$
#120
b10000 c
b0 #
b0 -
b0 E
b0 K
b0 ]
b0 F
b0 H
b0 C
b0 J
b0 g
0I
0f
b0 +
b0 2
b0 :
b0 =
b100000000 0
b100000000 6
b100000000 ;
b10 /
b10 5
b10 8
b10 <
1$
#130
0$
#140
b11 C
b11 J
b11 g
b111111110 `
b0 B
b0 b
b0 i
b11 @
b11 a
b11 d
b101001000000011 #
b101001000000011 -
b101001000000011 E
b101001000000011 K
b101001000000011 ]
b10000 c
b11111111 "
b11111111 ,
b11111111 D
b11111111 L
b11111111 ^
b1111 F
b1101 H
b1001 G
1I
b11111001110110000000 +
b11111001110110000000 2
b11111001110110000000 :
b11111001110110000000 =
b1000000000 0
b1000000000 6
b1000000000 ;
b100000000 /
b100000000 5
b100000000 8
b100000000 <
1$
#150
b11 \
0$
#160
b11 #
b11 -
b11 E
b11 K
b11 ]
b110 `
b10000 c
b11 "
b11 ,
b11 D
b11 L
b11 ^
b1101 F
b1101 G
b10 H
b11011101001010000000 +
b11011101001010000000 2
b11011101001010000000 :
b11011101001010000000 =
b1000000000000 0
b1000000000000 6
b1000000000000 ;
b1000000000 /
b1000000000 5
b1000000000 8
b1000000000 <
1$
#170
b11 V
0$
#180
b10 #
b10 -
b10 E
b10 K
b10 ]
b100 `
b100 C
b100 J
b100 g
b10 "
b10 ,
b10 D
b10 L
b10 ^
b10000 c
b100 @
b100 a
b100 d
b1100 G
b1110 F
b100 _
b1110 H
b11101100111010000100 +
b11101100111010000100 2
b11101100111010000100 :
b11101100111010000100 =
b1 0
b1 6
b1 ;
b1000000000000 /
b1000000000000 5
b1000000000000 8
b1000000000000 <
1$
#190
b110 C
b110 J
b110 g
b0 `
b10000 c
b110 @
b110 a
b110 d
b100 #
b100 -
b100 E
b100 K
b100 ]
b100 R
0$
#200
b100 #
b100 -
b100 E
b100 K
b100 ]
b10000 c
b1 B
b1 b
b1 i
b0 @
b0 a
b0 d
b100100100000110 C
b100100100000110 J
b100100100000110 g
b0 "
b0 ,
b0 D
b0 L
b0 ^
b1110 F
b0 _
1f
b1111 H
b0 G
b11100000111111000000 +
b11100000111111000000 2
b11100000111111000000 :
b11100000111111000000 =
b10 0
b10 6
b10 ;
b1 /
b1 5
b1 8
b1 <
1$
b100100100000110 %
b100100100000110 (
b100100100000110 >
b100100100000110 e
#210
b1001 4
b100100100000110 *
b100100100000110 1
b100100100000110 9
b100100100000110 A
b100100100000110 O
0$
#220
b10000 c
b0 #
b0 -
b0 E
b0 K
b0 ]
b0 F
b0 H
b0 C
b0 J
b0 g
0I
0f
b0 +
b0 2
b0 :
b0 =
b1000000 0
b1000000 6
b1000000 ;
b10 /
b10 5
b10 8
b10 <
1$
#230
0$
#240
b110 C
b110 J
b110 g
b0 B
b0 b
b0 i
b110 @
b110 a
b110 d
b100100100000110 #
b100100100000110 -
b100100100000110 E
b100100100000110 K
b100100100000110 ]
b1111 F
b1101 H
b10000 c
b1110 _
1I
b11110000110110001110 +
b11110000110110001110 2
b11110000110110001110 :
b11110000110110001110 =
b10000000 0
b10000000 6
b10000000 ;
b1000000 /
b1000000 5
b1000000 8
b1000000 <
1$
#250
b110 \
0$
#260
b110 #
b110 -
b110 E
b110 K
b110 ]
b1100 `
b110 "
b110 ,
b110 D
b110 L
b110 ^
b0 B
b0 b
b0 i
b1101 F
b110 C
b110 J
b110 g
1j
b1000 H
b1101 G
b10000 c
b110 @
b110 a
b110 d
b0 _
1h
b11011101100010110000 +
b11011101100010110000 2
b11011101100010110000 :
b11011101100010110000 =
b1000000000000 0
b1000000000000 6
b1000000000000 ;
b10000000 /
b10000000 5
b10000000 8
b10000000 <
1$
#270
b110 N
b10000 )
b10000 .
b10000 7
b10000 ?
b10000 k
0$
#280
b1000 `
b100 #
b100 -
b100 E
b100 K
b100 ]
b1000 G
b1010 C
b1010 J
b1010 g
b10000 c
b1010 @
b1010 a
b1010 d
b1110 F
b100 _
0h
b1110 H
b11101000111010100100 +
b11101000111010100100 2
b11101000111010100100 :
b11101000111010100100 =
b1 0
b1 6
b1 ;
b1000000000000 /
b1000000000000 5
b1000000000000 8
b1000000000000 <
1$
#290
b1010 #
b1010 -
b1010 E
b1010 K
b1010 ]
b1100 C
b1100 J
b1100 g
b100 `
b10000 c
b1100 @
b1100 a
b1100 d
b10 "
b10 ,
b10 D
b10 L
b10 ^
b1100 G
0j
b11101100111010000100 +
b11101100111010000100 2
b11101100111010000100 :
b11101100111010000100 =
b1010 R
b0 )
b0 .
b0 7
b0 ?
b0 k
0$
