ControlUnit/OutputLogic.v
module OutputLogic(
  state,  //current state
  status, //signals from processor status register
  ir, //the value of the instruction register
  ctrlword,  //a 18-bit control word to manage the datapath
  rw_mem //signal asserted when the main memory is asserted
);

  input  wire[12:0] state;
  input  wire[4:0]  status;
  input  wire[15:0] ir; //instruction
  output wire[19:0] ctrlword;
  output wire       rw_mem;

  //Address A[3]
  assign ctrlword[19] = state[0]  | 
                        state[2]  & ir[4] |
                        state[5]  |
                        state[6]  & (ir[10] | ir[9] |ir[8]) |
                        state[7] & ~ir[7] & (ir[10] | ir[9] |ir[8]) |
                        state[8]  |
                        state[9]  |
                        state[10] |
                        state[11] |
                        state[12] & (~status[4] | status[4] & (ir[10] | ir[9] | ir[8]));
  //Address A[2]
  assign ctrlword[18] = state[0]  |
                        state[2]  & (~ir[4] & ir[2] | ir[4])|
                        state[3]  & ir[7] |
                        state[4]  & ir[7] |
                        state[5]  |
                        state[6]  |
                        state[7] & ~ir[7] & (ir[10] | ir[9] |ir[8]) |
                        state[8] & ~ir[11] |
                        state[9]  |
                        state[10] |
                        state[11] |
                        state[12] & (~status[4] | status[4] & (ir[10] | ir[9] | ir[8]));

  //Address A[1]
  assign ctrlword[17] = state[0] |
                        state[2] & (~ir[4] & ir[1] | ir[4]) |
                        state[3] & ir[6] |
                        state[4] & ir[6] |
                        state[6] |
                        state[8] |
                        state[9] & ir[11] |
                        state[10] |
                        state[11] |
                        state[12] & (~status[4] | status[4] & (ir[10] | ir[9] | ir[8]));
  
  //Address A[0]
  assign ctrlword[16] = state[2] & (~ir[4] & ir[0] | ir[4]) |
                        state[3] & ir[5] |
                        state[4] & ir[5] |
                        state[5] |
                        state[6] |
                        state[7] & ~ir[7] & (ir[10] | ir[9] |ir[8]) |
                        state[8] & ~ir[11]|
                        state[9] |
                        state[11];
 
  //Address B[3]
  assign ctrlword[15] = state[2] & ir[4] |
                        state[3] |
                        state[6] |
                        state[7] |
                        state[8] |
                        state[9] |
                        state[10] |
                        state[11] |
                        state[12];
  //Address B[2]
  assign ctrlword[14] = state[2] & ir[2] |
                        state[3] |
                        state[4] & ir[2] |
                        state[5] & ir[10] |
                        state[6] & ~(ir[10 | ir[9] | ir[8]]) |
                        state[7] |
                        state[9] |
                        state[10] |
                        state[11] |
                        state[12] & ~status[4];
  //Address B[1]
  assign ctrlword[13] = state[2] & (~ir[4] & ir[1] | ir[4]) |
                        state[4] & ir[1] |
                        state[5] & ir[9] |
                        state[8] & ir[11] |
                        state[10] |
                        state[11];
  //Address B[0]
  assign ctrlword[12] = state[2] & (~ir[4] & ir[0] | ir[4] & ir[3]) |
                        state[3] |
                        state[4] & ir[0] |
                        state[5] & ir[8] |
                        state[6] & (ir[10] | ir[9] | ir[8]) |
                        state[7] |
                        state[8] |
                        state[9] |
                        state[11];
  //Address D[3]
  assign ctrlword[11]  = ~(state[1] |
                          state[3] | 
                          state[5] |
                          state[9] |
                          state[10]);

  //Address D[2]
  assign ctrlword[10]  = state[0] |
                        state[2] |
                        state[3] & ir[10] |
                        state[4] |
                        state[5] & ir[10] |
                        state[6] |
                        state[8] |
                        state[9] & ir[10] |
                        state[10] |
                        state[12];
  
  //Address D[1]
  assign ctrlword[9]  = state[0] |
                        state[3] & ir[9] |
                        state[5] & ir[9] |
                        state[9] & ir[9] |
                        state[10] |
                        state[12];
  
  //Address D[0]
  assign ctrlword[8]  = state[0] |
                        state[2] |
                        state[3] & ir[8] |
                        state[4] |
                        state[5] & ir[8] |
                        state[6] |
                        state[8] |
                        state[9] & ir[8] |
                        state[10];
  //rw file register
  assign ctrlword[7]  = ~(state[1] | 
                          state[5] & ir[11]);
  //Data selection
  assign ctrlword[6]  = state[0] |
                        state[5] & ~ir[11];

  //Write PSR
  assign ctrlword[5]  =      (state[3] & ~ir[4]  &  ir[3]) |
                  state[7] & ( ~ir[10] & ~ir[9]  & ~ir[8] | //jump
                               ~ir[10] & ~ir[9]  &  ir[8] | //ba
                            ~status[0] & ~ir[10] &  ir[9] & ~ir[8] | //bne
                             status[0] & ~ir[10] &  ir[9] &  ir[8] | //be
 ~status[0] & ~(status[1] ^ status[2]) &  ir[10] & ~ir[9] & ~ir[8] | //bg
  status[0] |  (status[1] ^ status[2]) &  ir[10] & ~ir[9] &  ir[8] | //ble
              ~(status[1] ^ status[2]) &  ir[10] &  ir[9] & ~ir[8] | //bge
               (status[1] ^ status[2]) &  ir[10] &  ir[9] &  ir[8] ) |//bl
                             state[11] |
                             state[12] & status[4];
  //set displacement             
  assign ctrlword[4] = state[7] & (     
                                         ~ir[10] & ~ir[9] & ~ir[8] | //jump
                                         ~ir[10] & ~ir[9] &  ir[8] | //ba
                           ~status[0]  & ~ir[10] &  ir[9] & ~ir[8] | //bne
                            status[0]  & ~ir[10] &  ir[9] &  ir[8] | //be
 ~status[0] & ~(status[1] ^ status[2]) &  ir[10] & ~ir[9] & ~ir[8] | //bg
  status[0] |  (status[1] ^ status[2]) &  ir[10] & ~ir[9] &  ir[8] | //ble
              ~(status[1] ^ status[2]) &  ir[10] &  ir[9] & ~ir[8] | //bge
               (status[1] ^ status[2]) &  ir[10] &  ir[9] &  ir[8] 
                                   ) |
                       state[11];

  
  //operational code[3]
  assign ctrlword[3]  = state[3] & ir[14] |
                        state[9] & ir[11];
  
  //operational code[2]
  assign ctrlword[2]  = state[3] & ir[13] |
                        state[4] |
                        state[6] & ~(ir[10] | ir[9] | ir[8]) |
                        state[7] & ir[7] |
                        state[9] & ir[11] |
                        state[11] |
                        state[12];

  //operational code[1]
  assign ctrlword[1]  = state[3] & ir[12];

  //operational code[0]
  assign ctrlword[0]  = state[2] & ir[4] & ir[3] |
                        state[3] & ir[11] |
                        state[4] & ir[4] |
                        state[7] & (~(ir[10] | ir[9] | ir[8]) | ir[7]);

  assign rw_mem = state[5] & ir[11];

endmodule // OutputLogic

ControlUnit/State.v
module State(
  d, //each of the inputs of the FFD integrating the memory of the M machine
  q, //each of the outputs of the FFD
  clk, //clock signal
  preset //Signal that reset the control unit to the IF state
);

  input  wire[12:0] d; //next state logic
  input  wire       clk, preset; //Obvious, isn't it?
  output reg[12:0]  q; //current state

  always @(posedge clk) begin
    if (preset) 
      q <= 13'b0000000000001;
    else
      q <= d;
  end

endmodule // State

ControlUnit/NextStateLogic.v
module NextStateLogic(
  opc1,     //operational code indicating the instruction format
  opc2,     //operational code indicating the functional operation 
  state,    //Memory of the Mealey machine
  nextstate //Output of the next-state-logic module
);

  input  wire[12:0] state;
  input  wire       opc1;
  input  wire[3:0]  opc2;
  output wire[12:0] nextstate;

  //Instruction fetch
  assign nextstate[0] = state[12];

  //Instruction decode
  assign nextstate[1] = state[0];

  //Operand fetch in microop
  assign nextstate[2] = state[1] & ~opc1 & (~(opc2[3] ^ opc2[2]) | //Logic and shift
                                   ~opc2[3] & opc2[2] & ~opc2[1] | //add
                                   ~opc2[1] & ~opc2[0] ); //mult
  //Instruction execution in microop
  assign nextstate[3] = state[2];

  //Operand fetch in memory instructions
  assign nextstate[4] = state[1] & ~opc1 & ~opc2[3] & opc2[2] & opc2[1];
  
  //Instruction execution in memory instructions
  assign nextstate[5] = state[4];

  //Operand fetch in jump instructions
  assign nextstate[6] = state[1] & ~opc1 & opc2[3] & ~opc2[2] & ~opc2[1] & opc2[0];

  //Instruction execution in jump instructions
  assign nextstate[7] = state[6];

  //Operand fetch in set-constant instructions
  assign nextstate[8] = state[1] & opc2[3] & ~opc2[2] & opc2[1];

  //Instruction execution in set-constant instructions
  assign nextstate[9] = state[8];

  //Link program counter
  assign nextstate[10] = state[1] & opc1;

  //Link PC in call instruction
  assign nextstate[11] = state[10];

  //Update program counter
  assign nextstate[12] = state[3] | state[5] | state[7] | state[9] | state[11];
  
endmodule // NextStateLogic

ControlUnit/ControlUnit.v
//`include "NextStateLogic.v"
//`include "State.v"
//`include "OutputLogic.v"
`include "ControlUnit/NextStateLogic.v"
`include "ControlUnit/State.v"
`include "ControlUnit/OutputLogic.v"

module ControlUnit(
  clk,         //clock signal
  reset,       //signal resetting the control unit to the IF state
  instruction, //an instruction from the IR register
  status,      //processor status
  ctrlword,    //control word to manage the datapath
  rw_mem       //signal that indicates the operation mode of the main memory
);

  //Port definition
  input  wire       clk, reset;
  input  wire[4:0]  status; //d, v, c, z, n
  input  wire[15:0] instruction;
  output wire[19:0] ctrlword;
  output wire       rw_mem;

  //Internal signals
  wire[12:0] state, nextstate;

  NextStateLogic nsl_unit(
    instruction[15],    //instruction format
    instruction[14:11], //functional operation
    state,              //memory
    nextstate           //output of the nsl module
  );

  State state_unit(
    nextstate, //the input of the memory
    state,     //the output of the memory
    clk,       //the clock signal
    reset      //the reset signal
  );

  OutputLogic ol_unit(
    state,       //output memory
    status,      //output from the PSR register
    instruction, //an instruction from the IR register
    ctrlword,    //the control word generated by the control unit
    rw_mem
  );

endmodule // ControUnit

Datapath/Basic/Mux2x1p.v
`ifndef MUX2X1_V
`define	MUX2X1_V

module Mux2x1(a, b, sel, y);
	
  parameter width = 1;
  input wire[width-1:0] a, b;
  input wire sel;
	output reg[width-1:0] y;
	
	always @(*)
	begin
		if (sel == 1'b0)
			y = a;
		else 
			y = b;
	end

endmodule

`endif

Datapath/PSR/ProcessorStatusRegister.v
//Author: Adán G. Medrano-Chávez
`ifndef PSR_V
`define PSR_V

module ProcessorStatusRegister(
    clk,          //clk signal
    reset,        //reset signal
    rw,           //PSR_rw signal
    displacement, //the set-displacement signal
    flags,        //status of an operation (V, C, Z, N)
    status        //the content of the PSR register
);


    input wire clk, reset, rw, displacement;
    input wire[3:0] flags;
    output reg[4:0] status;
    
    always @ (posedge clk or reset) begin
        if (rw) begin
            status <= {displacement,flags};
        end
        if (reset) begin
            status <= 5'b00000;
        end
    end

endmodule

`endif

Datapath/SimpleFunctionalUnit/FunctionalUnit.v
`ifndef SIMPLE_FU_V
`define SIMPLE_FU_V

module FunctionalUnit(
  a, //main operand to perform microoperations
  b, //supporting operand
  opcode, //operational code for microoperations
  result, //a result
  status //flags CVZN
);

  input wire[15:0] a, b;
  input wire[3:0] opcode;
  output reg[15:0] result;
  output reg[3:0] status;

  reg[16:0] carry; //Internal reg keeping all generated carries
  integer i;

  //Computes result
  always @(*) begin
    casex (opcode)
      4'b0000: result = a & b;
      4'b0001: result = a | b;
      4'b0010: result = ~a;
      4'b0011: result = a ^ b;
      4'b01x0: result = a + b + opcode[0];
      4'b01x1: result = a + ~b + opcode[0];
      4'b10xx: result = a[7:0] * b[7:0];
      4'b1100: result = a << b[3:0];
      4'b1101: result = a >> b[3:0];
      4'b1110: result = a <<< b[3:0];
      default: result = a >>> b[3:0];  
    endcase
  end

  //Computes flags
  //Note that this code is not sinthetizable
  //TODO: Compute carries hierarchically 
  always @(*) begin
    carry[0]  = opcode[0];
    status[0] = result[15];
    status[1] = ~|result;
    for (i = 0; i < 16 ; i = i + 1) begin
      carry[i+1] = a[i]&b[i] | (a[i]^b[i]) & carry[i];
    end
    status[2] = carry[16];
    status[3] = carry[16] ^ carry[15];
  end

endmodule // FunctionalUnit

`endif

Datapath/FileRegister/FileRegister.v
`ifndef FILE_REGISTER_V
`define FILE_REGISTER_V

module FileRegister(
    clk,
    reset,
    addrA,
    addrB,
    addrD,
    rw,
    data,
    busA,
    busB,
    ir
);

    localparam width = 16;
    input wire clk, reset, rw; //Clock signal and read/write signal
    input wire[3:0] addrA, addrB, addrD; //Address of buses A, B, and D
    input wire[width-1:0] data;
    output reg[width-1:0] busA, busB;
    reg[width-1:0] register[7:0];//Memory
    reg[width-1:0] displacement;
    reg[width-1:0] maskl;
    reg[width-1:0] pimm4;
    reg[width-1:0] nimm4;
    reg[width-1:0] const2;
    reg[width-1:0] temp0;
    reg[width-1:0] pc;
    output reg[width-1:0] ir;
        
    
    always @ (reset) begin
        if (reset) begin
            register[0]  <= 16'h0000;
            register[1]  <= 16'h0000;
            register[2]  <= 16'h0000;
            register[3]  <= 16'h0000;
            register[4]  <= 16'h0000;
            register[5]  <= 16'h0000;
            register[6]  <= 16'h0000;
            register[7]  <= 16'h0000;
            displacement <= 16'h0000;
            maskl        <= 16'h00FF;
            pimm4        <= 16'h000F;
            nimm4        <= 16'hFFF8;
            const2       <= 16'h0002;
            temp0        <= 16'h0000;
            pc           <= 16'h0000;
            ir           <= 16'h0000;
        end
    end
    
    always @ (posedge clk) begin        
        if (addrD == 4'h1 && rw)
            register[1] <= data;
        else if (addrD == 4'h2 && rw)
            register[2] <= data;
        else if (addrD == 4'h3 && rw)
            register[3] <= data;
        else if (addrD == 4'h4 && rw)
            register[4] <= data;
        else if (addrD == 4'h5 && rw)
            register[5] <= data;
        else if (addrD == 4'h6 && rw)
            register[6] <= data;
        else if (addrD == 4'h7 && rw)
            register[7] <= data;
        else if (addrD == 4'h8 && rw)
            displacement <= data;
        else if (addrD == 4'hD && rw)
            temp0 <= data;
        else if (addrD == 4'hE && rw)
            pc <= data;
        else if (addrD == 4'hF && rw)
            ir <= data;
        else begin
            register[0] <= 16'h0000;
            maskl <= 16'h00FF; //maskl
            pimm4 <= 16'h000F; //pimm4
            nimm4 <= 16'hFFF8; //nimm4
            const2 <= 16'h0002;//const2
        end
    end

    always @ (addrA or addrB) begin
        //Bus A
        if (addrA == 4'h0)
            busA = register[0];
        else if (addrA == 4'h1)
            busA = register[1];
        else if (addrA == 4'h2)
            busA = register[2];
        else if (addrA == 4'h3)
            busA = register[3];
        else if (addrA == 4'h4)
            busA = register[4];
        else if (addrA == 4'h5)
            busA = register[5];
        else if (addrA == 4'h6)
            busA = register[6];
        else if (addrA == 4'h7)
            busA = register[7];
        else if (addrA == 4'h8)
            busA = displacement;
        else if (addrA == 4'h9)
            busA = maskl;
        else if (addrA == 4'hA)
            busA = pimm4;
        else if (addrA == 4'hB)
            busA = nimm4;
        else if (addrA == 4'hC)
            busA = const2;
        else if (addrA == 4'hD)
            busA = temp0;
        else if (addrA == 4'hE)
            busA = pc;
        else
            busA = ir;
        //Bus B
        if (addrB == 4'h0)
            busB = register[0];
        else if (addrB == 4'h1)
            busB = register[1];
        else if (addrB == 4'h2)
            busB = register[2];
        else if (addrB == 4'h3)
            busB = register[3];
        else if (addrB == 4'h4)
            busB = register[4];
        else if (addrB == 4'h5)
            busB = register[5];
        else if (addrB == 4'h6)
            busB = register[6];
        else if (addrB == 4'h7)
            busB = register[7];
        else if (addrB == 4'h8)
            busB = displacement;
        else if (addrB == 4'h9)
            busB = maskl;
        else if (addrB == 4'hA)
            busB = pimm4;
        else if (addrB == 4'hB)
            busB = nimm4;
        else if (addrB == 4'hC)
            busB = const2;
        else if (addrB == 4'hD)
            busB = temp0;
        else if (addrB == 4'hE)
            busB = pc;
        else
            busB = ir;
    end

endmodule //Fileregister

`endif

Datapath/Datapath.v
`ifndef DATAPATH_V
`define DATAPATH_V

`ifdef PROCESSOR_V
  `include "Datapath/SimpleFunctionalUnit/FunctionalUnit.v"
  `include "Datapath/FileRegister/FileRegister.v"
  `include "Datapath/Basic/Mux2x1p.v"
  `include "Datapath/PSR/ProcessorStatusRegister.v"
`else
  `include "SimpleFunctionalUnit/FunctionalUnit.v"
  `include "FileRegister/FileRegister.v"
  `include "Basic/Mux2x1p.v"
  `include "PSR/ProcessorStatusRegister.v"
`endif

//The first line in the port module is the control word determining
//the datapath behavior
//The second line is the clock signal
//The last line is the output of the datapath, status contains the
//the flags VCNZ, the bus A conveys the data address to the 
//main memory and busB contains the data to be stored

module Datapath(
  clk,
  reset,
  ctrlword,
  instruction,
  status,
  dataIn,
  busA,
  busB
);

    input wire clk, reset;
    //{addrA}{addrb}{addrD}{FRrw}{seld}{PSRrw}{d}{opcode}
    input wire[19:0] ctrlword;
    input wire[15:0] dataIn;
    
    output wire[15:0] instruction, busA, busB;
    output wire[4:0] status;//D V C N Z flags
    
    /*Internal signals*/
    wire[15:0] result; //Result of the Functional Unit
    wire[15:0] dataBus; //Output of the MUX D
    wire[3:0] flags; //The status of an operation (V C N Z)

    FileRegister file_register_u(
        dataBus,          //data bus
        busA,             //address bus
        busB,             //data output bus
        instruction,      //the content of the IR register
        ctrlword[19:16],  //addrA
        ctrlword[15:12],  //addrB
        ctrlword[11:8],   //addrD
        reset,            //reset signal
        ctrlword[7],      //~read signal
        clk               //clock signal
    );

    //FunctionalUnit(a, b, opcode, y, status)
    FunctionalUnit functional_u(
        busA,          //Operand A from file register
        busB,          //output data bus
        ctrlword[3:0], //opcode
        result,        //Result from the funtional unit
        flags          //The status of an operation
    );
    
    //ProcessorStatusRegister(clk, reset, rw, displacement, flags, status)
    ProcessorStatusRegister psr_u(
        clk,         //clk signal
        reset,       //reset signal
        ctrlword[5], //PSR_rw signal
        ctrlword[4], //the set-displacement signal
        flags,       //status of an operation
        status       //the content of the PSR register
    );

    //module Mux2x1(a, b, sel, y);
    defparam muxd.width = 16;
    Mux2x1 muxd(
        result,      //Result from the functional unit
        dataIn,      //Data from the main memory
        ctrlword[6], //Data selection signal
        dataBus      //Input of the file register
    );

endmodule //module Datapath

`endif

Processor.v
`include "Datapath/Datapath.v"
`include "ControlUnit/ControlUnit.v"

module Processor(
  dataIn, //data or instructions comming from the main memory
  busA,   //Data comming from the bus A of the datapath
  busB,   //Data comming from the bus B of the datapath
  rw,     //signal indicating whether the main memory is to be written or not
  reset,  //signal reseting the processor
  clk     //clock signal
);

  input wire[15:0] dataIn;
  input wire clk, reset;
  output wire[15:0] busA, busB;
  output wire rw;
  
  //Internal signals
  wire[19:0] ctrlword;
  wire[15:0] instruction;
  wire[4:0] status; //d v c n z
  
  Datapath datapath_unit(
    clk,
    reset,
    ctrlword,
    instruction,
    status,
    dataIn,
    busA,
    busB
  );

  ControlUnit control_unit(
    clk,
    reset,
    instruction,
    status,
    ctrlword,
    rw
  );

endmodule //Processor

testbench.v
`include "Processor.v"
`timescale 1ns/100ps

module testbench;

  //outputs
  wire[15:0] busA, busB;
  wire rw;
  //inputs
  reg[15:0] dataIn;
  reg reset, clk;
  
  
  Processor mARC(//marcee
    dataIn, //data or instructions comming from the main memory
    busA,   //Data comming from the bus A of the datapath
    busB,   //Data comming from the bus B of the datapath
    rw,     //signal indicating whether the main memory is to be written or not
    reset,  //signal reseting the processor
    clk    //clock signal
  );
  
  always begin
    #1 clk = ~clk;
  end
  
  initial begin
    $dumpfile("marcee.vcd");
    $dumpvars(0, testbench);
    clk = 1;
    reset = 1;
    dataIn = 16'b0101000101000000; //setlow 64, %r1
    #0.5;
    reset = 0;
    #9.5;
    dataIn = 16'b0101101000000001; //sethi 1, %r2
    #10;
    dataIn = 16'b1111100000000010; //call 0xF004 (61444)
    #10;
    dataIn = 16'b0010100000101010; //subcc %r1, %r2, %r0
    #10;
    dataIn = 16'b0100110100000110; //ble 3 !%pc <-- %pc + 6
    #10;
    if (busA == 16'hF008) begin
      dataIn = 16'b0000101100100000; //mov %r1, %r3
      #10;
      dataIn = 16'b0100100100000100; //ba 2 !%pc <-- %pc + 4
      #10;
    end
    else begin
      dataIn = 16'b0000101101000000; //mov %r2, %r3
      #10;
    end
    dataIn = 16'b0100100000000111; //jmp %r7
    #10;
    dataIn = 16'b0101111000001000; //sethi 8, %r6 !%r6 <-- 2048
    #10;
    dataIn = 16'b0011101111000000; //st %r3, %r6
    #10 $finish;
  end
  
endmodule //testbench

marcee.vcd
$date
	Thu Nov 24 00:07:36 2016
$end
$version
	Icarus Verilog
$end
$timescale
	100ps
$end
$scope module testbench $end
$var wire 1 ! rw $end
$var wire 16 " busB [15:0] $end
$var wire 16 # busA [15:0] $end
$var reg 1 $ clk $end
$var reg 16 % dataIn [15:0] $end
$var reg 1 & reset $end
$scope module mARC $end
$var wire 1 $ clk $end
$var wire 16 ' dataIn [15:0] $end
$var wire 1 & reset $end
$var wire 5 ( status [4:0] $end
$var wire 1 ! rw $end
$var wire 16 ) instruction [15:0] $end
$var wire 20 * ctrlword [19:0] $end
$var wire 16 + busB [15:0] $end
$var wire 16 , busA [15:0] $end
$scope module control_unit $end
$var wire 1 $ clk $end
$var wire 1 & reset $end
$var wire 5 - status [4:0] $end
$var wire 13 . state [12:0] $end
$var wire 1 ! rw_mem $end
$var wire 13 / nextstate [12:0] $end
$var wire 16 0 instruction [15:0] $end
$var wire 20 1 ctrlword [19:0] $end
$scope module nsl_unit $end
$var wire 1 2 opc1 $end
$var wire 4 3 opc2 [3:0] $end
$var wire 13 4 state [12:0] $end
$var wire 13 5 nextstate [12:0] $end
$upscope $end
$scope module ol_unit $end
$var wire 1 ! rw_mem $end
$var wire 5 6 status [4:0] $end
$var wire 13 7 state [12:0] $end
$var wire 16 8 ir [15:0] $end
$var wire 20 9 ctrlword [19:0] $end
$upscope $end
$scope module state_unit $end
$var wire 1 $ clk $end
$var wire 13 : d [12:0] $end
$var wire 1 & preset $end
$var reg 13 ; q [12:0] $end
$upscope $end
$upscope $end
$scope module datapath_unit $end
$var wire 1 $ clk $end
$var wire 20 < ctrlword [19:0] $end
$var wire 16 = dataIn [15:0] $end
$var wire 1 & reset $end
$var wire 5 > status [4:0] $end
$var wire 16 ? result [15:0] $end
$var wire 16 @ instruction [15:0] $end
$var wire 4 A flags [3:0] $end
$var wire 16 B dataBus [15:0] $end
$var wire 16 C busB [15:0] $end
$var wire 16 D busA [15:0] $end
$scope module file_register_u $end
$var wire 4 E addrA [3:0] $end
$var wire 4 F addrB [3:0] $end
$var wire 4 G addrD [3:0] $end
$var wire 1 $ clk $end
$var wire 1 & reset $end
$var wire 1 H rw $end
$var wire 16 I data [15:0] $end
$var reg 16 J busA [15:0] $end
$var reg 16 K busB [15:0] $end
$var reg 16 L const2 [15:0] $end
$var reg 16 M displacement [15:0] $end
$var reg 16 N ir [15:0] $end
$var reg 16 O maskl [15:0] $end
$var reg 16 P nimm4 [15:0] $end
$var reg 16 Q pc [15:0] $end
$var reg 16 R pimm4 [15:0] $end
$var reg 16 S temp0 [15:0] $end
$upscope $end
$scope module functional_u $end
$var wire 16 T a [15:0] $end
$var wire 16 U b [15:0] $end
$var wire 4 V opcode [3:0] $end
$var reg 17 W carry [16:0] $end
$var reg 16 X result [15:0] $end
$var reg 4 Y status [3:0] $end
$var integer 32 Z i [31:0] $end
$upscope $end
$scope module muxd $end
$var wire 16 [ a [15:0] $end
$var wire 16 \ b [15:0] $end
$var wire 1 ] sel $end
$var reg 16 ^ y [15:0] $end
$upscope $end
$scope module psr_u $end
$var wire 1 $ clk $end
$var wire 1 _ displacement $end
$var wire 4 ` flags [3:0] $end
$var wire 1 & reset $end
$var wire 1 a rw $end
$var reg 5 b status [4:0] $end
$upscope $end
$upscope $end
$upscope $end
$upscope $end
$enddefinitions $end
#0
$dumpvars
b0 b
0a
b10 `
0_
b101000101000000 ^
1]
b101000101000000 \
b0 [
b10000 Z
b10 Y
b0 X
b0 W
b0 V
b0 U
b0 T
b0 S
b1111 R
b0 Q
b1111111111111000 P
b11111111 O
b0 N
b0 M
b10 L
b0 K
b0 J
b101000101000000 I
1H
b1111 G
b0 F
b1110 E
b0 D
b0 C
b101000101000000 B
b10 A
b0 @
b0 ?
b0 >
b101000101000000 =
b11100000111111000000 <
b1 ;
b10 :
b11100000111111000000 9
b0 8
b1 7
b0 6
b10 5
b1 4
b0 3
02
b11100000111111000000 1
b0 0
b10 /
b1 .
b0 -
b0 ,
b0 +
b11100000111111000000 *
b0 )
b0 (
b101000101000000 '
1&
b101000101000000 %
1$
b0 #
b0 "
0!
$end
#5
0&
#10
0$
#20
b0 E
b0 G
b0 B
b0 I
b0 ^
0H
0]
b0 *
b0 1
b0 9
b0 <
b100000000 /
b100000000 5
b100000000 :
b1010 3
b10 .
b10 4
b10 7
b10 ;
b101000101000000 )
b101000101000000 0
b101000101000000 8
b101000101000000 @
b101000101000000 N
1$
#30
0$
#40
b1000000 B
b1000000 I
b1000000 ^
b1110000000 W
b0 A
b0 Y
b0 `
b1000000 ?
b1000000 X
b1000000 [
b11111111 "
b11111111 +
b11111111 C
b11111111 K
b11111111 U
b10000 Z
b101000101000000 #
b101000101000000 ,
b101000101000000 D
b101000101000000 J
b101000101000000 T
b1111 E
b1101 G
b1001 F
1H
b11111001110110000000 *
b11111001110110000000 1
b11111001110110000000 9
b11111001110110000000 <
b1000000000 /
b1000000000 5
b1000000000 :
b100000000 .
b100000000 4
b100000000 7
b100000000 ;
1$
#50
0$
#60
b10000000 W
b10000 Z
b1000000 "
b1000000 +
b1000000 C
b1000000 K
b1000000 U
b1000000 #
b1000000 ,
b1000000 D
b1000000 J
b1000000 T
b1101 E
b1101 F
b1 G
b11011101000110000000 *
b11011101000110000000 1
b11011101000110000000 9
b11011101000110000000 <
b1000000000000 /
b1000000000000 5
b1000000000000 :
b1000000000 .
b1000000000 4
b1000000000 7
b1000000000 ;
b1000000 S
1$
#70
0$
#80
b0 W
b10 B
b10 I
b10 ^
b10 "
b10 +
b10 C
b10 K
b10 U
b0 #
b0 ,
b0 D
b0 J
b0 T
b10000 Z
b10 ?
b10 X
b10 [
b1100 F
b1110 E
b100 V
b1110 G
b11101100111010000100 *
b11101100111010000100 1
b11101100111010000100 9
b11101100111010000100 <
b1 /
b1 5
b1 :
b1000000000000 .
b1000000000000 4
b1000000000000 7
b1000000000000 ;
1$
#90
0$
#100
b10 #
b10 ,
b10 D
b10 J
b10 T
b10000 Z
b10 A
b10 Y
b10 `
b0 ?
b0 X
b0 [
b101101000000001 B
b101101000000001 I
b101101000000001 ^
b0 "
b0 +
b0 C
b0 K
b0 U
b1110 E
b0 V
1]
b1111 G
b0 F
b11100000111111000000 *
b11100000111111000000 1
b11100000111111000000 9
b11100000111111000000 <
b10 /
b10 5
b10 :
b1 .
b1 4
b1 7
b1 ;
b10 Q
1$
b101101000000001 %
b101101000000001 '
b101101000000001 =
b101101000000001 \
#110
0$
#120
b10000 Z
b0 #
b0 ,
b0 D
b0 J
b0 T
b0 E
b0 G
b0 B
b0 I
b0 ^
0H
0]
b0 *
b0 1
b0 9
b0 <
b1011 3
b100000000 /
b100000000 5
b100000000 :
b101101000000001 )
b101101000000001 0
b101101000000001 8
b101101000000001 @
b101101000000001 N
b10 .
b10 4
b10 7
b10 ;
1$
#130
0$
#140
b1000 B
b1000 I
b1000 ^
b11111111111110000 W
b10000 Z
b100 A
b100 Y
b100 `
b1000 ?
b1000 X
b1000 [
b1111111111111000 "
b1111111111111000 +
b1111111111111000 C
b1111111111111000 K
b1111111111111000 U
b1111 #
b1111 ,
b1111 D
b1111 J
b1111 T
b1010 E
b1101 G
b1011 F
1H
b10101011110110000000 *
b10101011110110000000 1
b10101011110110000000 9
b10101011110110000000 <
b1000000000 /
b1000000000 5
b1000000000 :
b100000000 .
b100000000 4
b100000000 7
b100000000 ;
1$
#150
0$
#160
b0 W
b1000 "
b1000 +
b1000 C
b1000 K
b1000 U
b100000000 B
b100000000 I
b100000000 ^
b1101 F
b10000 Z
b0 A
b0 Y
b0 `
b100000000 ?
b100000000 X
b100000000 [
b10 G
b101101000000001 #
b101101000000001 ,
b101101000000001 D
b101101000000001 J
b101101000000001 T
b1100 V
b1111 E
b11111101001010001100 *
b11111101001010001100 1
b11111101001010001100 9
b11111101001010001100 <
b1000000000000 /
b1000000000000 5
b1000000000000 :
b1000 S
b1000000000 .
b1000000000 4
b1000000000 7
b1000000000 ;
1$
#170
0$
#180
b100 B
b100 I
b100 ^
b100 W
b10000 Z
b100 ?
b100 X
b100 [
b10 "
b10 +
b10 C
b10 K
b10 U
b10 #
b10 ,
b10 D
b10 J
b10 T
b100 V
b1100 F
b1110 E
b1110 G
b11101100111010000100 *
b11101100111010000100 1
b11101100111010000100 9
b11101100111010000100 <
b1 /
b1 5
b1 :
b1000000000000 .
b1000000000000 4
b1000000000000 7
b1000000000000 ;
1$
#190
0$
#200
b0 W
b10000 Z
b10 A
b10 Y
b10 `
b0 ?
b0 X
b0 [
b1111100000000010 B
b1111100000000010 I
b1111100000000010 ^
b0 "
b0 +
b0 C
b0 K
b0 U
b100 #
b100 ,
b100 D
b100 J
b100 T
b1110 E
b0 V
1]
b1111 G
b0 F
b11100000111111000000 *
b11100000111111000000 1
b11100000111111000000 9
b11100000111111000000 <
b10 /
b10 5
b10 :
b100 Q
b1 .
b1 4
b1 7
b1 ;
1$
b1111100000000010 %
b1111100000000010 '
b1111100000000010 =
b1111100000000010 \
#210
0$
#220
b10000 Z
b0 #
b0 ,
b0 D
b0 J
b0 T
b0 E
b0 G
b0 B
b0 I
b0 ^
0H
0]
b0 *
b0 1
b0 9
b0 <
b10000000000 /
b10000000000 5
b10000000000 :
b1111 3
12
b10 .
b10 4
b10 7
b10 ;
b1111100000000010 )
b1111100000000010 0
b1111100000000010 8
b1111100000000010 @
b1111100000000010 N
1$
#230
0$
#240
b100 B
b100 I
b100 ^
b1000 W
b10000 Z
b0 A
b0 Y
b0 `
b100 ?
b100 X
b100 [
b100 "
b100 +
b100 C
b100 K
b100 U
b100 #
b100 ,
b100 D
b100 J
b100 T
b1110 E
1H
b1110 F
b111 G
b11101110011110000000 *
b11101110011110000000 1
b11101110011110000000 9
b11101110011110000000 <
b100000000000 /
b100000000000 5
b100000000000 :
b10000000000 .
b10000000000 4
b10000000000 7
b10000000000 ;
1$
#250
0$
