Datapath/SimpleFunctionalUnit/FunctionalUnit.v
`ifndef SIMPLE_FU_V
`define SIMPLE_FU_V

module FunctionalUnit(
  a, //main operand to perform microoperations
  b, //supporting operand
  opcode, //operational code for microoperations
  result, //a result
  status //flags CVZN
);

  input wire[15:0] a, b;
  input wire[3:0] opcode;
  output reg[15:0] result;
  output reg[3:0] status;

  reg[16:0] carry; //Internal reg keeping all generated carries
  integer i;

  //Computes result
  always @(*) begin
    casex (opcode)
      4'b0000: result = a & b;
      4'b0001: result = a | b;
      4'b0010: result = ~a;
      4'b0011: result = a ^ b;
      4'b01x0: result = a + b + opcode[0];
      4'b01x1: result = a + ~b + opcode[0];
      4'b10xx: result = a[7:0] * b[7:0];
      4'b1100: result = a << b[3:0];
      4'b1101: result = a >> b[3:0];
      4'b1110: result = a <<< b[3:0];
      default: result = a >>> b[3:0];  
    endcase
  end

  //Computes flags
  //Note that this code is not sinthetizable
  //TODO: Compute carries hierarchically 
  always @(*) begin
    carry[0]  = opcode[0];
    status[0] = result[15];
    status[1] = ~|result;
    for (i = 0; i < 16 ; i = i + 1) begin
      carry[i+1] = a[i]&b[i] | (a[i]^b[i]) & carry[i];
    end
    status[2] = carry[16];
    status[3] = carry[16] ^ carry[15];
  end

endmodule // FunctionalUnit

`endif

Datapath/SimpleFunctionalUnit/tb.v
`include "FunctionalUnit.v"
`timescale 1ns/100ps

module testbench;

  wire[15:0] result;
  wire[3:0] status;
  reg[15:0] a, b;
  reg[3:0] opcode;

  FunctionalUnit fu(a, b, opcode, result, status);

  always begin
    #1 opcode = opcode + 1;
  end

  initial begin
    $dumpfile("functional_unit.vcd");
    $dumpvars(0, testbench);
    a = 16'h00FF;
    b = 16'h0007;
    opcode = 0;
    #17 $finish;
  end

endmodule // testbench

Datapath/SimpleFunctionalUnit/functional_unit.vcd
$date
	Fri Nov 25 12:11:04 2016
$end
$version
	Icarus Verilog
$end
$timescale
	100ps
$end
$scope module testbench $end
$var wire 4 ! status [3:0] $end
$var wire 16 " result [15:0] $end
$var reg 16 # a [15:0] $end
$var reg 16 $ b [15:0] $end
$var reg 4 % opcode [3:0] $end
$scope module fu $end
$var wire 16 & a [15:0] $end
$var wire 16 ' b [15:0] $end
$var wire 4 ( opcode [3:0] $end
$var reg 17 ) carry [16:0] $end
$var reg 16 * result [15:0] $end
$var reg 4 + status [3:0] $end
$var integer 32 , i [31:0] $end
$upscope $end
$upscope $end
$enddefinitions $end
#0
$dumpvars
b10000 ,
b0 +
b111 *
b111111110 )
b0 (
b111 '
b11111111 &
b0 %
b111 $
b11111111 #
b111 "
b0 !
$end
#10
b10000 ,
b111111111 )
b11111111 "
b11111111 *
b1 %
b1 (
#20
b10000 ,
b1 !
b1 +
b111111110 )
b1111111100000000 "
b1111111100000000 *
b10 %
b10 (
#30
b10000 ,
b0 !
b0 +
b111111111 )
b11111000 "
b11111000 *
b11 %
b11 (
#40
b10000 ,
b111111110 )
b100000110 "
b100000110 *
b100 %
b100 (
#50
b10000 ,
b111111111 )
b11111000 "
b11111000 *
b101 %
b101 (
#60
b10000 ,
b111111110 )
b100000110 "
b100000110 *
b110 %
b110 (
#70
b10000 ,
b111111111 )
b11111000 "
b11111000 *
b111 %
b111 (
#80
b10000 ,
b111111110 )
b11011111001 "
b11011111001 *
b1000 %
b1000 (
#90
b10000 ,
b111111111 )
b1001 %
b1001 (
#100
b10000 ,
b111111110 )
b1010 %
b1010 (
#110
b10000 ,
b111111111 )
b1011 %
b1011 (
#120
b10000 ,
b111111110 )
b111111110000000 "
b111111110000000 *
b1100 %
b1100 (
#130
b10000 ,
b111111111 )
b1 "
b1 *
b1101 %
b1101 (
#140
b10000 ,
b111111110 )
b111111110000000 "
b111111110000000 *
b1110 %
b1110 (
#150
b10000 ,
b111111111 )
b1 "
b1 *
b1111 %
b1111 (
#160
b10000 ,
b111111110 )
b111 "
b111 *
b0 %
b0 (
#170
b10000 ,
b111111111 )
b11111111 "
b11111111 *
b1 %
b1 (
