ControlUnit/OutputLogic.v
module OutputLogic(
  state,  //current state
  status, //signals from processor status register
  ir, //the value of the instruction register
  ctrlword,  //a 18-bit control word to manage the datapath
  rw_mem //signal asserted when the main memory is asserted
);

  input  wire[12:0] state;
  input  wire[4:0]  status;
  input  wire[15:0] ir; //instruction
  output wire[19:0] ctrlword;
  output wire       rw_mem;

  //Address A[3]
  assign ctrlword[19] = state[0]  | 
                        state[2]  & ir[4] |
                        state[5]  |
                        state[6]  & (ir[10] | ir[9] |ir[8]) |
                        state[7]  |
                        state[8]  |
                        state[9]  |
                        state[10] |
                        state[11] |
                        state[12] & (~status[4] | status[4] & (ir[10] | ir[9] | ir[8]));
  //Address A[2]
  assign ctrlword[18] = state[0]  |
                        state[2]  & (~ir[4] & ir[2] | ir[4])|
                        state[3]  & ir[7] |
                        state[4]  & ir[7] |
                        state[5]  |
                        state[6]  |
                        state[7]  |
                        state[8] & ~ir[11] |
                        state[9]  |
                        state[10] |
                        state[11] |
                        state[12] & (~status[4] | status[4] & (ir[10] | ir[9] | ir[8]));

  //Address A[1]
  assign ctrlword[17] = state[0] |
                        state[2] & (~ir[4] & ir[1] | ir[4]) |
                        state[3] & ir[6] |
                        state[4] & ir[6] |
                        state[6] |
                        state[8] |
                        state[9] & ir[11] |
                        state[10] |
                        state[11] |
                        state[12] & (~status[4] | status[4] & (ir[10] | ir[9] | ir[8]));
  
  //Address A[0]
  assign ctrlword[16] = state[2] & (~ir[4] & ir[0] | ir[4]) |
                        state[3] & ir[5] |
                        state[4] & ir[5] |
                        state[5] |
                        state[6] |
                        state[7] |
                        state[8] & ~ir[11]|
                        state[9] |
                        state[11];
 
  //Address B[3]
  assign ctrlword[15] = state[2] & ir[4] |
                        state[3] |
                        state[6] & ~(ir[10] | ir[9] |ir[8])|
                        state[7] |
                        state[8] |
                        state[9] |
                        state[10] |
                        state[11] |
                        state[12];
  //Address B[2]
  assign ctrlword[14] = state[2] & ir[2] |
                        state[3] |
                        state[4] & ir[2] |
                        state[5] & ir[10] |
                        state[6] & ~(ir[10 | ir[9] | ir[8]]) |
                        state[7] |
                        state[9] |
                        state[10] |
                        state[11] |
                        state[12] & ~status[4];
  //Address B[1]
  assign ctrlword[13] = state[2] & (~ir[4] & ir[1] | ir[4]) |
                        state[4] & ir[1] |
                        state[5] & ir[9] |
                        state[8] & ir[11] |
                        state[10] |
                        state[11];
  //Address B[0]
  assign ctrlword[12] = state[2] & (~ir[4] & ir[0] | ir[4] & ir[3]) |
                        state[3] |
                        state[4] & ir[0] |
                        state[5] & ir[8] |
                        state[7] |
                        state[8] |
                        state[9] |
                        state[11];
  //Address D[3]
  assign ctrlword[11]  = ~(state[1] |
                          state[3] | 
                          state[5] |
                          state[9] |
                          state[10]);

  //Address D[2]
  assign ctrlword[10]  = state[0] |
                        state[2] |
                        state[3] & ir[10] |
                        state[4] |
                        state[5] & ir[10] |
                        state[6] |
                        state[8] |
                        state[9] & ir[10] |
                        state[10] |
                        state[12];
  
  //Address D[1]
  assign ctrlword[9]  = state[0] |
                        state[3] & ir[9] |
                        state[5] & ir[9] |
                        state[9] & ir[9] |
                        state[10] |
                        state[12];
  
  //Address D[0]
  assign ctrlword[8]  = state[0] |
                        state[2] |
                        state[3] & ir[8] |
                        state[4] |
                        state[5] & ir[8] |
                        state[6] |
                        state[8] |
                        state[9] & ir[8] |
                        state[10];
  //rw file register
  assign ctrlword[7]  = ~(state[1] | 
                          state[5] & ir[11]);
  //Data selection
  assign ctrlword[6]  = state[0] |
                        state[5] & ~ir[11];

  //Write PSR
  //TODO Revisar la ecuación
  assign ctrlword[5]  =     (state[3] & ~ir[4]  &  ir[3]) |
                             state[7] & ((~ir[10] & ~ir[9] & ~ir[8]) | //jump
                                         (~ir[10] & ~ir[9] &  ir[8]) | //ba
                            (~status[0] & ~ir[10] &  ir[9] & ~ir[8]) | //bne
                             (status[0] & ~ir[10] &  ir[9] &  ir[8]) | //be
 (~status[0] & ~(status[1] ^ status[2]) &  ir[10] & ~ir[9] & ~ir[8] )| //bg
((status[0] |  (status[1] ^ status[2])) &  ir[10] & ~ir[9] &  ir[8]) | //ble
              (~(status[1] ^ status[2]) &  ir[10] &  ir[9] & ~ir[8]) | //bge
               ((status[1] ^ status[2]) &  ir[10] &  ir[9] &  ir[8]) ) |//bl
                             state[11] |
                             state[12] & status[4];
  //set displacement             
  assign ctrlword[4] = state[7] | state[11];

  
  //operational code[3]
  assign ctrlword[3]  = state[3] & ir[14] |
                        state[6] & (ir[10] | ir[9] |ir[8]) |
                        state[9] & ir[11];
  
  //operational code[2]
  assign ctrlword[2]  = state[3] & ir[13] |
                        state[4] |
                        state[6] & (ir[10] | ir[9] | ir[8]) |
                        state[9] & ir[11] |
                        state[11] |
                        state[12];

  //operational code[1]
  assign ctrlword[1]  = state[3] & ir[12] |
                        state[6] & (ir[10] | ir[9] | ir[8]);

  //operational code[0]
  assign ctrlword[0]  = state[2] & ir[4] & ir[3] |
                        state[3] & ir[11] |
                        state[4] & ir[4];

  assign rw_mem = state[5] & ir[11];

endmodule // OutputLogic

ControlUnit/State.v
module State(
  d, //each of the inputs of the FFD integrating the memory of the M machine
  q, //each of the outputs of the FFD
  clk, //clock signal
  preset //Signal that reset the control unit to the IF state
);

  input  wire[12:0] d; //next state logic
  input  wire       clk, preset; //Obvious, isn't it?
  output reg[12:0]  q; //current state

  always @(posedge clk) begin
    if (preset) 
      q <= 13'b0000000000001;
    else
      q <= d;
  end

endmodule // State

ControlUnit/NextStateLogic.v
module NextStateLogic(
  opc1,     //operational code indicating the instruction format
  opc2,     //operational code indicating the functional operation 
  state,    //Memory of the Mealey machine
  nextstate //Output of the next-state-logic module
);

  input  wire[12:0] state;
  input  wire       opc1;
  input  wire[3:0]  opc2;
  output wire[12:0] nextstate;

  //Instruction fetch
  assign nextstate[0] = state[12];

  //Instruction decode
  assign nextstate[1] = state[0];

  //Operand fetch in microop
  assign nextstate[2] = state[1] & ~opc1 & (~(opc2[3] ^ opc2[2]) | //Logic and shift
                                   ~opc2[3] & opc2[2] & ~opc2[1] | //add
                                   ~opc2[1] & ~opc2[0] ); //mult
  //Instruction execution in microop
  assign nextstate[3] = state[2];

  //Operand fetch in memory instructions
  assign nextstate[4] = state[1] & ~opc2[3] & opc2[2] & opc2[1];
  
  //Instruction execution in memory instructions
  assign nextstate[5] = state[4];

  //Operand fetch in jump instructions
  assign nextstate[6] = state[1] & opc2[3] & ~opc2[2] & ~opc2[1] & opc2[0];

  //Instruction execution in jump instructions
  assign nextstate[7] = state[6];

  //Operand fetch in set-constant instructions
  assign nextstate[8] = state[1] & opc2[3] & ~opc2[2] & opc2[1];

  //Instruction execution in set-constant instructions
  assign nextstate[9] = state[8];

  //Link program counter
  assign nextstate[10] = state[1] & opc1;

  //Link PC in call instruction
  assign nextstate[11] = state[10];

  //Update program counter
  assign nextstate[12] = state[3] | state[5] | state[7] | state[9] | state[11];
  
endmodule // NextStateLogic

ControlUnit/ControlUnit.v
//`include "NextStateLogic.v"
//`include "State.v"
//`include "OutputLogic.v"
`include "ControlUnit/NextStateLogic.v"
`include "ControlUnit/State.v"
`include "ControlUnit/OutputLogic.v"

module ControlUnit(
  clk,         //clock signal
  reset,       //signal resetting the control unit to the IF state
  instruction, //an instruction from the IR register
  status,      //processor status
  ctrlword,    //control word to manage the datapath
  rw_mem       //signal that indicates the operation mode of the main memory
);

  //Port definition
  input  wire       clk, reset;
  input  wire[4:0]  status; //d, v, c, z, n
  input  wire[15:0] instruction;
  output wire[19:0] ctrlword;
  output wire       rw_mem;

  //Internal signals
  wire[12:0] state, nextstate;

  NextStateLogic nsl_unit(
    instruction[15],    //instruction format
    instruction[14:11], //functional operation
    state,              //memory
    nextstate           //output of the nsl module
  );

  State state_unit(
    nextstate, //the input of the memory
    state,     //the output of the memory
    clk,       //the clock signal
    reset      //the reset signal
  );

  OutputLogic ol_unit(
    state,       //output memory
    status,      //output from the PSR register
    instruction, //an instruction from the IR register
    ctrlword,    //the control word generated by the control unit
    rw_mem
  );

endmodule // ControUnit

ControlUnit/testbench.v
`include "ControlUnit.v"
`timescale 1ns/100ps

module testbench;

  reg clk, reset;
  reg[4:0] status;
  reg[15:0] instruction;

  wire[19:0] ctrlword;
  wire rw_mem, rw_psr, set_disp;

  ControlUnit control_unit(clk, reset, instruction, status, ctrlword, rw_mem);

  always begin
    #1 clk = ~clk;
  end

  initial begin
    $dumpfile("controlunit.vcd");
    $dumpvars(0, testbench);    
    clk = 1;
    status = 0;
    reset = 1;
    //instruction =  16'b0010111100000011; //subcc %r0, %r3, %r7
    instruction     =  16'b0010001100100010; //subcc %r0, %r3, %r7
    #10 instruction =  16'b0011011100000001; //ld [%r1+%r0], %r7
    #10 instruction =  16'b0011111100010001; //st [%r1-%r0], %r7
    #10 instruction =  16'b0100100000000111; //jmpl
    #10 instruction =  16'b0100100111111111; //ba
    #10 instruction =  16'b0101011111111111; //setlow FF, %r7
    #10 instruction =  16'b0101111111111111; //sethi FF, %r7
    #10 instruction =  16'b1111111111110000; //call
    #12 $finish;
  end

endmodule // testbech;

ControlUnit/controlunit.vcd
$date
	Thu Dec  1 12:39:44 2016
$end
$version
	Icarus Verilog
$end
$timescale
	100ps
$end
$scope module testbench $end
$var wire 1 ! rw_mem $end
$var wire 20 " ctrlword [19:0] $end
$var reg 1 # clk $end
$var reg 16 $ instruction [15:0] $end
$var reg 1 % reset $end
$var reg 5 & status [4:0] $end
$scope module control_unit $end
$var wire 1 # clk $end
$var wire 16 ' instruction [15:0] $end
$var wire 1 % reset $end
$var wire 5 ( status [4:0] $end
$var wire 13 ) state [12:0] $end
$var wire 1 ! rw_mem $end
$var wire 13 * nextstate [12:0] $end
$var wire 20 + ctrlword [19:0] $end
$scope module nsl_unit $end
$var wire 1 , opc1 $end
$var wire 4 - opc2 [3:0] $end
$var wire 13 . state [12:0] $end
$var wire 13 / nextstate [12:0] $end
$upscope $end
$scope module ol_unit $end
$var wire 16 0 ir [15:0] $end
$var wire 1 ! rw_mem $end
$var wire 5 1 status [4:0] $end
$var wire 13 2 state [12:0] $end
$var wire 20 3 ctrlword [19:0] $end
$upscope $end
$scope module state_unit $end
$var wire 1 # clk $end
$var wire 13 4 d [12:0] $end
$var wire 1 % preset $end
$var reg 13 5 q [12:0] $end
$upscope $end
$upscope $end
$upscope $end
$enddefinitions $end
#0
$dumpvars
b1 5
b10 4
b11100000111111000000 3
b1 2
b0 1
b10001100100010 0
b10 /
b1 .
b100 -
0,
b11100000111111000000 +
b10 *
b1 )
b0 (
b10001100100010 '
b0 &
1%
b10001100100010 $
1#
b11100000111111000000 "
0!
$end
#10
0#
#20
b0 "
b0 +
b0 3
b100 *
b100 /
b100 4
b10 )
b10 .
b10 2
b10 5
1#
#30
0#
#40
b100010110110000000 "
b100010110110000000 +
b100010110110000000 3
b1000 *
b1000 /
b1000 4
b100 )
b100 .
b100 2
b100 5
1#
#50
0#
#60
b11101001110000100 "
b11101001110000100 +
b11101001110000100 3
b1000000000000 *
b1000000000000 /
b1000000000000 4
b1000 )
b1000 .
b1000 2
b1000 5
1#
#70
0#
#80
b11101100111010000100 "
b11101100111010000100 +
b11101100111010000100 3
b1 *
b1 /
b1 4
b1000000000000 )
b1000000000000 .
b1000000000000 2
b1000000000000 5
1#
#90
0#
#100
b11100000111111000000 "
b11100000111111000000 +
b11100000111111000000 3
b10 *
b10 /
b10 4
b1 )
b1 .
b1 2
b1 5
b110 -
1#
b11011100000001 $
b11011100000001 '
b11011100000001 0
#110
0#
#120
b0 "
b0 +
b0 3
b10000 *
b10000 /
b10000 4
b10 )
b10 .
b10 2
b10 5
1#
#130
0#
#140
b1110110000100 "
b1110110000100 +
b1110110000100 3
b100000 *
b100000 /
b100000 4
b10000 )
b10000 .
b10000 2
b10000 5
1#
#150
0#
#160
b11010111011111000000 "
b11010111011111000000 +
b11010111011111000000 3
b1000000000000 *
b1000000000000 /
b1000000000000 4
b100000 )
b100000 .
b100000 2
b100000 5
1#
#170
0#
#180
b11101100111010000100 "
b11101100111010000100 +
b11101100111010000100 3
b1 *
b1 /
b1 4
b1000000000000 )
b1000000000000 .
b1000000000000 2
b1000000000000 5
1#
#190
0#
#200
b11100000111111000000 "
b11100000111111000000 +
b11100000111111000000 3
b10 *
b10 /
b10 4
b1 )
b1 .
b1 2
b1 5
b111 -
1#
b11111100010001 $
b11111100010001 '
b11111100010001 0
#210
0#
#220
b0 "
b0 +
b0 3
b10000 *
b10000 /
b10000 4
b10 )
b10 .
b10 2
b10 5
1#
#230
0#
#240
b1110110000101 "
b1110110000101 +
b1110110000101 3
b100000 *
b100000 /
b100000 4
b10000 )
b10000 .
b10000 2
b10000 5
1#
#250
0#
#260
b11010111011100000000 "
b11010111011100000000 +
b11010111011100000000 3
1!
b1000000000000 *
b1000000000000 /
b1000000000000 4
b100000 )
b100000 .
b100000 2
b100000 5
1#
#270
0#
#280
0!
b11101100111010000100 "
b11101100111010000100 +
b11101100111010000100 3
b1 *
b1 /
b1 4
b1000000000000 )
b1000000000000 .
b1000000000000 2
b1000000000000 5
1#
#290
0#
#300
b11100000111111000000 "
b11100000111111000000 +
b11100000111111000000 3
b10 *
b10 /
b10 4
b1 )
b1 .
b1 2
b1 5
b1001 -
1#
b100100000000111 $
b100100000000111 '
b100100000000111 0
#310
0#
#320
b0 "
b0 +
b0 3
b1000000 *
b1000000 /
b1000000 4
b10 )
b10 .
b10 2
b10 5
1#
#330
0#
#340
b1111100110110000100 "
b1111100110110000100 +
b1111100110110000100 3
b10000000 *
b10000000 /
b10000000 4
b1000000 )
b1000000 .
b1000000 2
b1000000 5
1#
#350
0#
#360
b1101100010110001 "
b1101100010110001 +
b1101100010110001 3
b1000000000000 *
b1000000000000 /
b1000000000000 4
b10000000 )
b10000000 .
b10000000 2
b10000000 5
1#
#370
0#
#380
b11101100111010000100 "
b11101100111010000100 +
b11101100111010000100 3
b1 *
b1 /
b1 4
b1000000000000 )
b1000000000000 .
b1000000000000 2
b1000000000000 5
1#
#390
0#
#400
b11100000111111000000 "
b11100000111111000000 +
b11100000111111000000 3
b10 *
b10 /
b10 4
b1 )
b1 .
b1 2
b1 5
1#
b100100111111111 $
b100100111111111 '
b100100111111111 0
#410
0#
#420
b0 "
b0 +
b0 3
b1000000 *
b1000000 /
b1000000 4
b10 )
b10 .
b10 2
b10 5
1#
#430
0#
#440
b11111001110110000000 "
b11111001110110000000 +
b11111001110110000000 3
b10000000 *
b10000000 /
b10000000 4
b1000000 )
b1000000 .
b1000000 2
b1000000 5
1#
#450
0#
#460
b1101100010110101 "
b1101100010110101 +
b1101100010110101 3
b1000000000000 *
b1000000000000 /
b1000000000000 4
b10000000 )
b10000000 .
b10000000 2
b10000000 5
1#
#470
0#
#480
b11101100111010000100 "
b11101100111010000100 +
b11101100111010000100 3
b1 *
b1 /
b1 4
b1000000000000 )
b1000000000000 .
b1000000000000 2
b1000000000000 5
1#
#490
0#
#500
b11100000111111000000 "
b11100000111111000000 +
b11100000111111000000 3
b10 *
b10 /
b10 4
b1 )
b1 .
b1 2
b1 5
b1010 -
1#
b101011111111111 $
b101011111111111 '
b101011111111111 0
#510
0#
#520
b0 "
b0 +
b0 3
b100000000 *
b100000000 /
b100000000 4
b10 )
b10 .
b10 2
b10 5
1#
#530
0#
#540
b11111001110110000000 "
b11111001110110000000 +
b11111001110110000000 3
b1000000000 *
b1000000000 /
b1000000000 4
b100000000 )
b100000000 .
b100000000 2
b100000000 5
1#
#550
0#
#560
b11011101011110000000 "
b11011101011110000000 +
b11011101011110000000 3
b1000000000000 *
b1000000000000 /
b1000000000000 4
b1000000000 )
b1000000000 .
b1000000000 2
b1000000000 5
1#
#570
0#
#580
b11101100111010000100 "
b11101100111010000100 +
b11101100111010000100 3
b1 *
b1 /
b1 4
b1000000000000 )
b1000000000000 .
b1000000000000 2
b1000000000000 5
1#
#590
0#
#600
b11100000111111000000 "
b11100000111111000000 +
b11100000111111000000 3
b10 *
b10 /
b10 4
b1 )
b1 .
b1 2
b1 5
b1011 -
1#
b101111111111111 $
b101111111111111 '
b101111111111111 0
#610
0#
#620
b0 "
b0 +
b0 3
b100000000 *
b100000000 /
b100000000 4
b10 )
b10 .
b10 2
b10 5
1#
#630
0#
#640
b10101011110110000000 "
b10101011110110000000 +
b10101011110110000000 3
b1000000000 *
b1000000000 /
b1000000000 4
b100000000 )
b100000000 .
b100000000 2
b100000000 5
1#
#650
0#
#660
b11111101011110001100 "
b11111101011110001100 +
b11111101011110001100 3
b1000000000000 *
b1000000000000 /
b1000000000000 4
b1000000000 )
b1000000000 .
b1000000000 2
b1000000000 5
1#
#670
0#
#680
b11101100111010000100 "
b11101100111010000100 +
b11101100111010000100 3
b1 *
b1 /
b1 4
b1000000000000 )
b1000000000000 .
b1000000000000 2
b1000000000000 5
1#
#690
0#
#700
b11100000111111000000 "
b11100000111111000000 +
b11100000111111000000 3
b10 *
b10 /
b10 4
b1 )
b1 .
b1 2
b1 5
1,
b1111 -
1#
b1111111111110000 $
b1111111111110000 '
b1111111111110000 0
#710
0#
#720
b0 "
b0 +
b0 3
b10000000000 *
b10000000000 /
b10000000000 4
b10 )
b10 .
b10 2
b10 5
1#
#730
0#
#740
b11101110011110000000 "
b11101110011110000000 +
b11101110011110000000 3
b100000000000 *
b100000000000 /
b100000000000 4
b10000000000 )
b10000000000 .
b10000000000 2
b10000000000 5
1#
#750
0#
#760
b11111111100010110100 "
b11111111100010110100 +
b11111111100010110100 3
b1000000000000 *
b1000000000000 /
b1000000000000 4
b100000000000 )
b100000000000 .
b100000000000 2
b100000000000 5
1#
#770
0#
#780
b11101100111010000100 "
b11101100111010000100 +
b11101100111010000100 3
b1 *
b1 /
b1 4
b1000000000000 )
b1000000000000 .
b1000000000000 2
b1000000000000 5
1#
#790
0#
#800
b11100000111111000000 "
b11100000111111000000 +
b11100000111111000000 3
b10 *
b10 /
b10 4
b1 )
b1 .
b1 2
b1 5
1#
#810
0#
#820
b0 "
b0 +
b0 3
b10000000000 *
b10000000000 /
b10000000000 4
b10 )
b10 .
b10 2
b10 5
1#
